{
  "connectivity_resource_groups": {},
  "connectivity_tags": null,
  "hub_and_spoke_networks_settings": {},
  "hub_virtual_networks": {},
  "management_groups_enabled": true,
  "management_resources_enabled": true,
  "private_link_private_dns_zone_virtual_network_link_moved_blocks_enabled": false,
  "required_subscription_keys": [
    "connectivity",
    "management"
  ],
  "root_parent_management_group_id": "",
  "starter_locations_short": {},
  "subscription_ids": {
    "management": "85cfd850-a97a-4b21-a662-fcc1728a0854",
    "identity": "",
    "connectivity": "29417a59-d276-4daf-b9f1-491a287fa541",
    "security": ""
  }
}
